{
  "metadata": {
    "qualificationType": "International A Level",
    "session": "October 2024",
    "subject": "Accounting (2015)",
    "unit": "WAC11/01 - The Accounting System and Costing",
    "recordCount": 208,
    "timestamp": "2025-05-03T18:33:35.181Z"
  },
  "data": [
    {
      "RAW": 200,
      "UMS": 300,
      "GRADE": "Max Mark"
    },
    {
      "RAW": 200,
      "UMS": 300,
      "GRADE": "A"
    },
    {
      "RAW": 199,
      "UMS": 300,
      "GRADE": "A"
    },
    {
      "RAW": 198,
      "UMS": 300,
      "GRADE": "A"
    },
    {
      "RAW": 197,
      "UMS": 300,
      "GRADE": "A"
    },
    {
      "RAW": 196,
      "UMS": 300,
      "GRADE": "A"
    },
    {
      "RAW": 195,
      "UMS": 300,
      "GRADE": "A"
    },
    {
      "RAW": 194,
      "UMS": 300,
      "GRADE": "A"
    },
    {
      "RAW": 193,
      "UMS": 300,
      "GRADE": "A"
    },
    {
      "RAW": 192,
      "UMS": 300,
      "GRADE": "A"
    },
    {
      "RAW": 191,
      "UMS": 300,
      "GRADE": "A"
    },
    {
      "RAW": 190,
      "UMS": 300,
      "GRADE": "A"
    },
    {
      "RAW": 189,
      "UMS": 300,
      "GRADE": "A"
    },
    {
      "RAW": 188,
      "UMS": 300,
      "GRADE": "A"
    },
    {
      "RAW": 187,
      "UMS": 300,
      "GRADE": "A"
    },
    {
      "RAW": 186,
      "UMS": 300,
      "GRADE": "A"
    },
    {
      "RAW": 185,
      "UMS": 300,
      "GRADE": "A"
    },
    {
      "RAW": 184,
      "UMS": 300,
      "GRADE": "A"
    },
    {
      "RAW": 183,
      "UMS": 300,
      "GRADE": "A"
    },
    {
      "RAW": 182,
      "UMS": 300,
      "GRADE": "A"
    },
    {
      "RAW": 181,
      "UMS": 300,
      "GRADE": "A"
    },
    {
      "RAW": 180,
      "UMS": 300,
      "GRADE": "A"
    },
    {
      "RAW": 179,
      "UMS": 300,
      "GRADE": "A"
    },
    {
      "RAW": 178,
      "UMS": 299,
      "GRADE": "A"
    },
    {
      "RAW": 177,
      "UMS": 297,
      "GRADE": "A"
    },
    {
      "RAW": 176,
      "UMS": 296,
      "GRADE": "A"
    },
    {
      "RAW": 175,
      "UMS": 294,
      "GRADE": "A"
    },
    {
      "RAW": 174,
      "UMS": 293,
      "GRADE": "A"
    },
    {
      "RAW": 173,
      "UMS": 291,
      "GRADE": "A"
    },
    {
      "RAW": 172,
      "UMS": 290,
      "GRADE": "A"
    },
    {
      "RAW": 171,
      "UMS": 288,
      "GRADE": "A"
    },
    {
      "RAW": 170,
      "UMS": 287,
      "GRADE": "A"
    },
    {
      "RAW": 169,
      "UMS": 285,
      "GRADE": "A"
    },
    {
      "RAW": 168,
      "UMS": 284,
      "GRADE": "A"
    },
    {
      "RAW": 167,
      "UMS": 282,
      "GRADE": "A"
    },
    {
      "RAW": 166,
      "UMS": 281,
      "GRADE": "A"
    },
    {
      "RAW": 165,
      "UMS": 279,
      "GRADE": "A"
    },
    {
      "RAW": 164,
      "UMS": 278,
      "GRADE": "A"
    },
    {
      "RAW": 163,
      "UMS": 276,
      "GRADE": "A"
    },
    {
      "RAW": 162,
      "UMS": 275,
      "GRADE": "A"
    },
    {
      "RAW": 161,
      "UMS": 273,
      "GRADE": "A"
    },
    {
      "RAW": 160,
      "UMS": 272,
      "GRADE": "A"
    },
    {
      "RAW": 159,
      "UMS": 270,
      "GRADE": "A"
    },
    {
      "RAW": 158,
      "UMS": 269,
      "GRADE": "A"
    },
    {
      "RAW": 157,
      "UMS": 267,
      "GRADE": "A"
    },
    {
      "RAW": 156,
      "UMS": 266,
      "GRADE": "A"
    },
    {
      "RAW": 155,
      "UMS": 264,
      "GRADE": "A"
    },
    {
      "RAW": 154,
      "UMS": 263,
      "GRADE": "A"
    },
    {
      "RAW": 153,
      "UMS": 261,
      "GRADE": "A"
    },
    {
      "RAW": 152,
      "UMS": 260,
      "GRADE": "A"
    },
    {
      "RAW": 151,
      "UMS": 258,
      "GRADE": "A"
    },
    {
      "RAW": 150,
      "UMS": 257,
      "GRADE": "A"
    },
    {
      "RAW": 149,
      "UMS": 255,
      "GRADE": "A"
    },
    {
      "RAW": 148,
      "UMS": 254,
      "GRADE": "A"
    },
    {
      "RAW": 147,
      "UMS": 252,
      "GRADE": "A"
    },
    {
      "RAW": 146,
      "UMS": 251,
      "GRADE": "A"
    },
    {
      "RAW": 145,
      "UMS": 249,
      "GRADE": "A"
    },
    {
      "RAW": 144,
      "UMS": 248,
      "GRADE": "A"
    },
    {
      "RAW": 143,
      "UMS": 246,
      "GRADE": "A"
    },
    {
      "RAW": 142,
      "UMS": 245,
      "GRADE": "A"
    },
    {
      "RAW": 141,
      "UMS": 243,
      "GRADE": "A"
    },
    {
      "RAW": 140,
      "UMS": 242,
      "GRADE": "A"
    },
    {
      "RAW": 139,
      "UMS": 240,
      "GRADE": "A"
    },
    {
      "RAW": 139,
      "UMS": 240,
      "GRADE": "A"
    },
    {
      "RAW": 138,
      "UMS": 239,
      "GRADE": "B"
    },
    {
      "RAW": 137,
      "UMS": 237,
      "GRADE": "B"
    },
    {
      "RAW": 136,
      "UMS": 236,
      "GRADE": "B"
    },
    {
      "RAW": 135,
      "UMS": 234,
      "GRADE": "B"
    },
    {
      "RAW": 134,
      "UMS": 233,
      "GRADE": "B"
    },
    {
      "RAW": 133,
      "UMS": 231,
      "GRADE": "B"
    },
    {
      "RAW": 132,
      "UMS": 230,
      "GRADE": "B"
    },
    {
      "RAW": 131,
      "UMS": 228,
      "GRADE": "B"
    },
    {
      "RAW": 130,
      "UMS": 227,
      "GRADE": "B"
    },
    {
      "RAW": 129,
      "UMS": 225,
      "GRADE": "B"
    },
    {
      "RAW": 128,
      "UMS": 224,
      "GRADE": "B"
    },
    {
      "RAW": 127,
      "UMS": 222,
      "GRADE": "B"
    },
    {
      "RAW": 126,
      "UMS": 221,
      "GRADE": "B"
    },
    {
      "RAW": 125,
      "UMS": 219,
      "GRADE": "B"
    },
    {
      "RAW": 124,
      "UMS": 218,
      "GRADE": "B"
    },
    {
      "RAW": 123,
      "UMS": 216,
      "GRADE": "B"
    },
    {
      "RAW": 122,
      "UMS": 215,
      "GRADE": "B"
    },
    {
      "RAW": 121,
      "UMS": 213,
      "GRADE": "B"
    },
    {
      "RAW": 120,
      "UMS": 212,
      "GRADE": "B"
    },
    {
      "RAW": 119,
      "UMS": 210,
      "GRADE": "B"
    },
    {
      "RAW": 119,
      "UMS": 210,
      "GRADE": "B"
    },
    {
      "RAW": 118,
      "UMS": 209,
      "GRADE": "C"
    },
    {
      "RAW": 117,
      "UMS": 207,
      "GRADE": "C"
    },
    {
      "RAW": 116,
      "UMS": 206,
      "GRADE": "C"
    },
    {
      "RAW": 115,
      "UMS": 204,
      "GRADE": "C"
    },
    {
      "RAW": 114,
      "UMS": 203,
      "GRADE": "C"
    },
    {
      "RAW": 113,
      "UMS": 201,
      "GRADE": "C"
    },
    {
      "RAW": 112,
      "UMS": 200,
      "GRADE": "C"
    },
    {
      "RAW": 111,
      "UMS": 198,
      "GRADE": "C"
    },
    {
      "RAW": 110,
      "UMS": 197,
      "GRADE": "C"
    },
    {
      "RAW": 109,
      "UMS": 195,
      "GRADE": "C"
    },
    {
      "RAW": 108,
      "UMS": 194,
      "GRADE": "C"
    },
    {
      "RAW": 107,
      "UMS": 192,
      "GRADE": "C"
    },
    {
      "RAW": 106,
      "UMS": 191,
      "GRADE": "C"
    },
    {
      "RAW": 105,
      "UMS": 189,
      "GRADE": "C"
    },
    {
      "RAW": 104,
      "UMS": 188,
      "GRADE": "C"
    },
    {
      "RAW": 103,
      "UMS": 186,
      "GRADE": "C"
    },
    {
      "RAW": 102,
      "UMS": 185,
      "GRADE": "C"
    },
    {
      "RAW": 101,
      "UMS": 183,
      "GRADE": "C"
    },
    {
      "RAW": 100,
      "UMS": 182,
      "GRADE": "C"
    },
    {
      "RAW": 99,
      "UMS": 180,
      "GRADE": "C"
    },
    {
      "RAW": 99,
      "UMS": 180,
      "GRADE": "C"
    },
    {
      "RAW": 98,
      "UMS": 179,
      "GRADE": "D"
    },
    {
      "RAW": 97,
      "UMS": 177,
      "GRADE": "D"
    },
    {
      "RAW": 96,
      "UMS": 176,
      "GRADE": "D"
    },
    {
      "RAW": 95,
      "UMS": 174,
      "GRADE": "D"
    },
    {
      "RAW": 94,
      "UMS": 173,
      "GRADE": "D"
    },
    {
      "RAW": 93,
      "UMS": 171,
      "GRADE": "D"
    },
    {
      "RAW": 92,
      "UMS": 170,
      "GRADE": "D"
    },
    {
      "RAW": 91,
      "UMS": 168,
      "GRADE": "D"
    },
    {
      "RAW": 90,
      "UMS": 167,
      "GRADE": "D"
    },
    {
      "RAW": 89,
      "UMS": 165,
      "GRADE": "D"
    },
    {
      "RAW": 88,
      "UMS": 164,
      "GRADE": "D"
    },
    {
      "RAW": 87,
      "UMS": 162,
      "GRADE": "D"
    },
    {
      "RAW": 86,
      "UMS": 161,
      "GRADE": "D"
    },
    {
      "RAW": 85,
      "UMS": 159,
      "GRADE": "D"
    },
    {
      "RAW": 84,
      "UMS": 158,
      "GRADE": "D"
    },
    {
      "RAW": 83,
      "UMS": 156,
      "GRADE": "D"
    },
    {
      "RAW": 82,
      "UMS": 155,
      "GRADE": "D"
    },
    {
      "RAW": 81,
      "UMS": 153,
      "GRADE": "D"
    },
    {
      "RAW": 80,
      "UMS": 152,
      "GRADE": "D"
    },
    {
      "RAW": 79,
      "UMS": 150,
      "GRADE": "D"
    },
    {
      "RAW": 79,
      "UMS": 150,
      "GRADE": "D"
    },
    {
      "RAW": 78,
      "UMS": 148,
      "GRADE": "E"
    },
    {
      "RAW": 77,
      "UMS": 147,
      "GRADE": "E"
    },
    {
      "RAW": 76,
      "UMS": 145,
      "GRADE": "E"
    },
    {
      "RAW": 75,
      "UMS": 144,
      "GRADE": "E"
    },
    {
      "RAW": 74,
      "UMS": 142,
      "GRADE": "E"
    },
    {
      "RAW": 73,
      "UMS": 141,
      "GRADE": "E"
    },
    {
      "RAW": 72,
      "UMS": 139,
      "GRADE": "E"
    },
    {
      "RAW": 71,
      "UMS": 137,
      "GRADE": "E"
    },
    {
      "RAW": 70,
      "UMS": 136,
      "GRADE": "E"
    },
    {
      "RAW": 69,
      "UMS": 134,
      "GRADE": "E"
    },
    {
      "RAW": 68,
      "UMS": 133,
      "GRADE": "E"
    },
    {
      "RAW": 67,
      "UMS": 131,
      "GRADE": "E"
    },
    {
      "RAW": 66,
      "UMS": 129,
      "GRADE": "E"
    },
    {
      "RAW": 65,
      "UMS": 128,
      "GRADE": "E"
    },
    {
      "RAW": 64,
      "UMS": 126,
      "GRADE": "E"
    },
    {
      "RAW": 63,
      "UMS": 125,
      "GRADE": "E"
    },
    {
      "RAW": 62,
      "UMS": 123,
      "GRADE": "E"
    },
    {
      "RAW": 61,
      "UMS": 122,
      "GRADE": "E"
    },
    {
      "RAW": 60,
      "UMS": 120,
      "GRADE": "E"
    },
    {
      "RAW": 60,
      "UMS": 120,
      "GRADE": "E"
    },
    {
      "RAW": 59,
      "UMS": 118,
      "GRADE": "U"
    },
    {
      "RAW": 58,
      "UMS": 117,
      "GRADE": "U"
    },
    {
      "RAW": 57,
      "UMS": 115,
      "GRADE": "U"
    },
    {
      "RAW": 56,
      "UMS": 114,
      "GRADE": "U"
    },
    {
      "RAW": 55,
      "UMS": 112,
      "GRADE": "U"
    },
    {
      "RAW": 54,
      "UMS": 111,
      "GRADE": "U"
    },
    {
      "RAW": 53,
      "UMS": 109,
      "GRADE": "U"
    },
    {
      "RAW": 52,
      "UMS": 107,
      "GRADE": "U"
    },
    {
      "RAW": 51,
      "UMS": 106,
      "GRADE": "U"
    },
    {
      "RAW": 50,
      "UMS": 104,
      "GRADE": "U"
    },
    {
      "RAW": 49,
      "UMS": 103,
      "GRADE": "U"
    },
    {
      "RAW": 48,
      "UMS": 101,
      "GRADE": "U"
    },
    {
      "RAW": 47,
      "UMS": 99,
      "GRADE": "U"
    },
    {
      "RAW": 46,
      "UMS": 98,
      "GRADE": "U"
    },
    {
      "RAW": 45,
      "UMS": 96,
      "GRADE": "U"
    },
    {
      "RAW": 44,
      "UMS": 95,
      "GRADE": "U"
    },
    {
      "RAW": 43,
      "UMS": 93,
      "GRADE": "U"
    },
    {
      "RAW": 42,
      "UMS": 92,
      "GRADE": "U"
    },
    {
      "RAW": 41,
      "UMS": 90,
      "GRADE": "U"
    },
    {
      "RAW": 40,
      "UMS": 88,
      "GRADE": "U"
    },
    {
      "RAW": 39,
      "UMS": 86,
      "GRADE": "U"
    },
    {
      "RAW": 38,
      "UMS": 83,
      "GRADE": "U"
    },
    {
      "RAW": 37,
      "UMS": 81,
      "GRADE": "U"
    },
    {
      "RAW": 36,
      "UMS": 79,
      "GRADE": "U"
    },
    {
      "RAW": 35,
      "UMS": 77,
      "GRADE": "U"
    },
    {
      "RAW": 34,
      "UMS": 75,
      "GRADE": "U"
    },
    {
      "RAW": 33,
      "UMS": 72,
      "GRADE": "U"
    },
    {
      "RAW": 32,
      "UMS": 70,
      "GRADE": "U"
    },
    {
      "RAW": 31,
      "UMS": 68,
      "GRADE": "U"
    },
    {
      "RAW": 30,
      "UMS": 66,
      "GRADE": "U"
    },
    {
      "RAW": 29,
      "UMS": 64,
      "GRADE": "U"
    },
    {
      "RAW": 28,
      "UMS": 61,
      "GRADE": "U"
    },
    {
      "RAW": 27,
      "UMS": 59,
      "GRADE": "U"
    },
    {
      "RAW": 26,
      "UMS": 57,
      "GRADE": "U"
    },
    {
      "RAW": 25,
      "UMS": 55,
      "GRADE": "U"
    },
    {
      "RAW": 24,
      "UMS": 53,
      "GRADE": "U"
    },
    {
      "RAW": 23,
      "UMS": 50,
      "GRADE": "U"
    },
    {
      "RAW": 22,
      "UMS": 48,
      "GRADE": "U"
    },
    {
      "RAW": 21,
      "UMS": 46,
      "GRADE": "U"
    },
    {
      "RAW": 20,
      "UMS": 44,
      "GRADE": "U"
    },
    {
      "RAW": 19,
      "UMS": 42,
      "GRADE": "U"
    },
    {
      "RAW": 18,
      "UMS": 40,
      "GRADE": "U"
    },
    {
      "RAW": 17,
      "UMS": 37,
      "GRADE": "U"
    },
    {
      "RAW": 16,
      "UMS": 35,
      "GRADE": "U"
    },
    {
      "RAW": 15,
      "UMS": 33,
      "GRADE": "U"
    },
    {
      "RAW": 14,
      "UMS": 31,
      "GRADE": "U"
    },
    {
      "RAW": 13,
      "UMS": 29,
      "GRADE": "U"
    },
    {
      "RAW": 12,
      "UMS": 26,
      "GRADE": "U"
    },
    {
      "RAW": 11,
      "UMS": 24,
      "GRADE": "U"
    },
    {
      "RAW": 10,
      "UMS": 22,
      "GRADE": "U"
    },
    {
      "RAW": 9,
      "UMS": 20,
      "GRADE": "U"
    },
    {
      "RAW": 8,
      "UMS": 18,
      "GRADE": "U"
    },
    {
      "RAW": 7,
      "UMS": 15,
      "GRADE": "U"
    },
    {
      "RAW": 6,
      "UMS": 13,
      "GRADE": "U"
    },
    {
      "RAW": 5,
      "UMS": 11,
      "GRADE": "U"
    },
    {
      "RAW": 4,
      "UMS": 9,
      "GRADE": "U"
    },
    {
      "RAW": 3,
      "UMS": 7,
      "GRADE": "U"
    },
    {
      "RAW": 2,
      "UMS": 4,
      "GRADE": "U"
    },
    {
      "RAW": 1,
      "UMS": 2,
      "GRADE": "U"
    },
    {
      "RAW": 0,
      "UMS": 0,
      "GRADE": "U"
    },
    {
      "RAW": 0,
      "UMS": 0,
      "GRADE": "U"
    }
  ]
}